hggithub
