Metadata-Version: 1.0
Name: hg-github
Version: 0.1.3
Summary: A Mercurial extension for working with GitHub repositories
Home-page: http://github.com/stephenmcd/hg-github
Author: Stephen McDonald
Author-email: steve@jupo.org
License: BSD
Platform: UNKNOWN
Classifier: Development Status :: 4 - Beta
Classifier: Intended Audience :: Developers
Classifier: License :: OSI Approved :: BSD License
Classifier: Operating System :: POSIX
Classifier: Programming Language :: Python
Classifier: Topic :: Software Development :: Version Control
